{
  "category":[
    {"title": "Ноутбуки"},
    {"title": "Электроника"},
    {"title": "Компьютеры"},
    {"title": "Бытовая техника"},
    {"title": "Автотовары"},
    {"title": "Мебель"}
  ],
  "characteristic":[
    {"title": "Процессор"},
    {"title": "Частота процессора"},
    {"title": "Объем оперативной памяти"},
    {"title": "Объем жесткого диска"},
    {"title": "Диагональ экрана"},
    {"title": "Видеокарта"},
    {"title": "Вес"},
    {"title": "Оптический привод"},
    {"title": "4G LTE"},
    {"title": "Bluetooth"},
    {"title": "Wi-Fi"}
  ],
  "product":[
    {"title": "Ноутбук Xiaomi Mi Notebook Pro 15.6\"", "category": 1, "price": 6120000, "rating": 4.5, "image": "https://i1.rozetka.ua/goods/4225293/xiaomi_mi_notebook_pro_15_6_jyu4036cn_images_4225293328.jpg"},
    {"title": "Ноутбук HP EliteBook 1040 G4 14\"", "category": 1, "price": 12010000, "rating": 5.0, "image": "https://i2.rozetka.ua/goods/7457108/hp_4qy60es_images_7457108610.jpg"},
    {"title": "Ноутбук Lenovo IdeaPad 530S-14IKB 14\"", "category": 1, "price": 5960000, "rating": 4, "image": "https://i2.rozetka.ua/goods/5726418/lenovo_ideapad_530s_14ikb_81eu00fgra_images_5726418240.jpg"},
    {"title": "Ноутбук Dell Latitude 5491 14\"", "category": 1, "price": 9950000, "rating": 4.3, "image": "https://i1.rozetka.ua/goods/5956719/dell_n006l549114_ubu_images_5956719072.jpg"},
    {"title": "Ноутбук Apple MacBook Pro 13 with Retina display", "category": 1, "price": 7995000, "rating": 4.8, "image": "https://i2.rozetka.ua/goods/6820783/50198222_images_6820783302.jpg"}
  ],
  "charact_value":[
    {"characteristic": 1, "product": 5, "value": "Intel Core i5"},
    {"characteristic": 2, "product": 5, "value": "2.3 - 3.6 ГГц"},
    {"characteristic": 3, "product": 5, "value": "8 ГБ"},
    {"characteristic": 4, "product": 5, "value": "SSD 128 ГБ"},
    {"characteristic": 5, "product": 5, "value": "13\""},
    {"characteristic": 6, "product": 5, "value": "Intel Iris Plus Graphics 640"},
    {"characteristic": 7, "product": 5, "value": "1.37 кг"},
    {"characteristic": 8, "product": 5, "value": "нет"},
    {"characteristic": 9, "product": 5, "value": "нет"},
    {"characteristic": 10, "product": 5, "value": "есть"},
    {"characteristic": 11, "product": 5, "value": "есть"},
    {"characteristic": 1, "product": 4, "value": "Core i7-8850H"},
    {"characteristic": 2, "product": 4, "value": "2.6 - 4.3 ГГц"},
    {"characteristic": 3, "product": 4, "value": "16 ГБ"},
    {"characteristic": 4, "product": 4, "value": "SSD 512 ГБ"},
    {"characteristic": 5, "product": 4, "value": "14\""},
    {"characteristic": 6, "product": 4, "value": "Intel UHD Graphics 630"},
    {"characteristic": 7, "product": 4, "value": "1.65 кг"},
    {"characteristic": 8, "product": 4, "value": "нет"},
    {"characteristic": 9, "product": 4, "value": "нет"},
    {"characteristic": 10, "product": 4, "value": "есть"},
    {"characteristic": 11, "product": 4, "value": "есть"},
    {"characteristic": 1, "product": 3, "value": "Core i5-8250U"},
    {"characteristic": 2, "product": 3, "value": "1.6 - 3.4 ГГц"},
    {"characteristic": 3, "product": 3, "value": "16 ГБ"},
    {"characteristic": 4, "product": 3, "value": "SSD 512 ГБ"},
    {"characteristic": 5, "product": 3, "value": "14\""},
    {"characteristic": 6, "product": 3, "value": "Intel UHD Graphics 620"},
    {"characteristic": 7, "product": 3, "value": "1.59 кг"},
    {"characteristic": 8, "product": 3, "value": "нет"},
    {"characteristic": 9, "product": 3, "value": "нет"},
    {"characteristic": 10, "product": 3, "value": "есть"},
    {"characteristic": 11, "product": 3, "value": "есть"},
    {"characteristic": 1, "product": 2, "value": "Core i7-7500U"},
    {"characteristic": 2, "product": 2, "value": "2.7 - 3.5 ГГц"},
    {"characteristic": 3, "product": 2, "value": "16 ГБ"},
    {"characteristic": 4, "product": 2, "value": "SSD 512 ГБ"},
    {"characteristic": 5, "product": 2, "value": "14\""},
    {"characteristic": 6, "product": 2, "value": "Intel UHD Graphics 620"},
    {"characteristic": 7, "product": 2, "value": "1.36 кг"},
    {"characteristic": 8, "product": 2, "value": "нет"},
    {"characteristic": 9, "product": 2, "value": "есть"},
    {"characteristic": 10, "product": 2, "value": "есть"},
    {"characteristic": 11, "product": 2, "value": "есть"},
    {"characteristic": 1, "product": 1, "value": "Core i5-8250U"},
    {"characteristic": 2, "product": 1, "value": "1.6 - 3.4 ГГц"},
    {"characteristic": 3, "product": 1, "value": "8 ГБ"},
    {"characteristic": 4, "product": 1, "value": "SSD 256 ГБ"},
    {"characteristic": 5, "product": 1, "value": "15.6\""},
    {"characteristic": 6, "product": 1, "value": "nVidia GeForce MX150, 2 ГБ"},
    {"characteristic": 7, "product": 1, "value": "1.95 кг"},
    {"characteristic": 8, "product": 1, "value": "нет"},
    {"characteristic": 9, "product": 1, "value": "нет"},
    {"characteristic": 10, "product": 1, "value": "есть"},
    {"characteristic": 11, "product": 1, "value": "есть"}
  ],
  "comment":[
    {"product": 3, "user": null, "comment": "Порадовала быстрая обработка заказа и доставка. Ноутбук прекрасно подходит для работы. Не для игр. Батарея долго держит заряд. Очень качественные материалы. Дисплей и винчестер - на высоте"},
    {"product": 3, "user": null, "comment": "Какое покрытие монитора мат или глянец?"},
    {"product": 2, "user": null, "comment": "А игры потянет?"},
    {"product": 1, "user": null, "comment": "Может сохраню чужие деньги. Крайне не совету. этот ноутбук. У меня минимальная комплектация Сборка в ноуте на троечку с минусом. Нижняя крышка скрипит. При открытии слышен хруст (т.к шарнир из пластика). После пари недель пользования расшатываются некоторые кнопки. Или как проще написать, не знаю. В общем трещать стали при нажатии сильнее остальных кнопок. При этом ноутбук не падал. Никуда его не носил, он все время стоит на столе. Про охлаждение это вообще отдельная история. Перед включением кулеры ( а они включаться раз в минут 20-30 при работе в браузере с 2 вкладками при темп. 30-40 градусов) издают странный звук. И это в сбалансирован режиме. В играх это просто. Звук как от ракеты. Мой старый асус 11 года с дискретной грф. в раза 2 тише работал в играх. И греется он ужас как. Над шарниром палец положить нельзя. Я понимаю что он не для игр. Пишу для справки. И это в сбалансирован режиме. Веб камера это просто ужас. На уровне ноутов 10-го года. Если прислушаться кулеры издают странный звук. Треск, скрежет, писк. Правда не очень громкий. И это не я один такой. На 4pda много кто про это писал.У некоторых начинаются проблемы с системой охлаждения через месяц второй. А сначала все нормально. Ночью при полной тишине это дико бесит. Это не правильная центровка кулеров (насколько я прочитал на 4пда). Ах да, еще подсветка клавиатуры никак не настраивается и когда ноутбук закрыт между экраном и клавой огромная щель с пол сантиметра. Хотя на рендерах такого нет)) Просто знайте что вы покупаете."},
    {"product": 1, "user": null, "comment": "За два месяца использования почти все впечатления положительные. Для работы хватает с головой. Одновременно были открыты Автокад, Инвентор с сборкой, трансляция в браузере и фото, и все вместе тянуло меньше 6 гб оперативной памяти. ССД диск очень быстрый, система загружается за 12 секунд. Винда работает нормально, правда язык интерфейса с украинского на русский криво поменялся и местами попадается укаинский, но думаю, что это проблема самой системы. Из-за компактности корпуса сильно греется, если запускать какие-либо игры. При высоких настройках в Доте за 15-20 минут игры разогревается до 80-85 градусов, дольше играть не рисковал. При низких настройках 70-75 градусов на протяжении часа. Шум заметный, но мне не мешает. Экран хорош, но в светлое время суток в нем все отражается, как в зеркале. Лично мне матовый был бы приятнее. Теперь к проблеме. После 2х месяцев эксплуатации заметил треск в одном из вентиляторов, если наклонять ноутбук в разные стороны. Похоже на люфт крыльчатки на оси. Буду отправлять в сервис... Общее впечатление о ноуте сильно подпортилось, но думаю, что за эти деньги вряд ли найдется другой вариант с лучшим качеством сборки и материалов."},
    {"product": 1, "user": null, "comment": "сегодня привезли ноутбук. первые впечатления только положительные)"},
    {"product": 1, "user": null, "comment": "Что хочу сказать,кто говорит что он плох,то они просто им не пользовались. Там стоит достаточно мощная дискретка,для своего размера ноута . Да,греется над шарниром,но это норма. Это ультрабук. У него такой корпус,если процессор не выше 100 градусов,с ним всё будет хорошо. Но не стоит этим переусердствовать,так как большие температуры не скажутся на процессоре,а на других комплектующих которые находятся близко к нему. Процессор работает на отлично,если поставить максимальную производительность,при стандартном теплопакете в 15вт(я пробовал и повышать),при питании от сети он работает на 3.5-3.7 ггц,при стабильной нагрузке без троттлинга. Пробовал запускать игры,но запускал только BF3(высокие настройки,играть отлично,60 фпс), LoL(League of Legends) высокие 140 фпс, и STALKER Lost Alpha DC,высокие настройки и DirectX 11,с детальной прорисовкой и детализацией + динамичиские освещения. Я не знаю у кого как,но у меня на максимальной загрузке,его почти не слышно,куллера ооочень тихо работают."},
    {"product": 5, "user": null, "comment": "2 порта type-c выглядит, конечно, как издевательство. Когда ноут на зарядке, остается всего один порт, чего зачастую нехватает. Отсутствие hdmi, тоже напрягает. Пришлось купить хаб, что нихрена не добавляет мобильности и удобства. Батарею, по сравнению с прошкой 2015, урезали, время работы от батареи заметно уменьшилось. Клава по приятнее. Радует меньший вес, но при этом на не самых тяжелых приложениях (аля webstorm) ноут начинает заметно шуметь. В общем, цена неадекватная... Если уж и брать, то раннии прошки."},
    {"product": 5, "user": null, "comment": "Долго выбирал ноутбук (был на примете еще del xps 13) для работы (программирование). Выбрал - не пожалел. Очень удобная операционная система. Красивый ui + возможности unix систем. Клавиатура и трекпад вместе с шорткатами/жестами, значительно облегчают работу. Удобно работать и без мышки. Звук превосходный. Экран тоже. Легкий - можно кинуть в рюкзак. Для длительного путешествия зарядка будет добавлять лишний вес (около 200г). Заряжается часа за полтора, что очень-очень круто."},
    {"product": 5, "user": null, "comment": "В целом, замечательный девайс, но учитывая, что проблема с wifi известна давно (есть исследование intel 2012 года \"USB 3.0* Radio Frequency Interference on 2.4 GHz Devices\"), а они продолжают располагать антенну близко к порта usb и тот факт, что нарвался на брак - ставлю среднюю оценку. Для такой компании это непростительно, я считаю."}
  ]
}
